README.txt
buildout.cfg
setup.py
src/zc/__init__.py
src/zc.sourcerelease.egg-info/PKG-INFO
src/zc.sourcerelease.egg-info/SOURCES.txt
src/zc.sourcerelease.egg-info/dependency_links.txt
src/zc.sourcerelease.egg-info/entry_points.txt
src/zc.sourcerelease.egg-info/namespace_packages.txt
src/zc.sourcerelease.egg-info/not-zip-safe
src/zc.sourcerelease.egg-info/requires.txt
src/zc.sourcerelease.egg-info/top_level.txt
src/zc/sourcerelease/CHANGES.txt
src/zc/sourcerelease/README.txt
src/zc/sourcerelease/__init__.py
src/zc/sourcerelease/tests.py