Metadata-Version: 1.0
Name: zc.sourcerelease
Version: 0.3.1
Summary: Utility script to create source releases from buildouts
Home-page: http://www.python.org/pypi/zc.sourcerelease
Author: Jim Fulton
Author-email: jim@zope.com
License: ZPL 2.1
Platform: UNKNOWN
